mqfactory/MessageQueue.py
mqfactory/Queue.py
mqfactory/__init__.py
mqfactory/tools.py
mqfactory/message/__init__.py
mqfactory/message/format/__init__.py
mqfactory/message/format/js.py
mqfactory/message/security/__init__.py
mqfactory/message/security/rsa.py
mqfactory/store/__init__.py
mqfactory/store/mongo.py
mqfactory/transport/__init__.py
mqfactory/transport/mqtt.py
mqfactory/transport/qos.py
tests/__init__.py
tests/conftest.py
tests/test_Acknowledging.py
tests/test_IntegratePersistJsonAck.py
tests/test_IntegrateSigning.py
tests/test_JsonFormatting.py
tests/test_MQTTTransport.py
tests/test_Message.py
tests/test_MessageQueue.py
tests/test_MessageStore.py
tests/test_MessageStoreQueue.py
tests/test_MongoStore.py
tests/test_Policy.py
tests/test_Queue.py
tests/test_RsaSignature.py
tests/test_Signing.py
mqfactory-0.0.4.dist-info/LICENSE.txt
mqfactory-0.0.4.dist-info/METADATA
mqfactory-0.0.4.dist-info/WHEEL
mqfactory-0.0.4.dist-info/top_level.txt
mqfactory-0.0.4.dist-info/RECORD
