Metadata-Version: 2.1
Name: mqfactory
Version: 0.0.4
Summary: Framework for building message queues.
Home-page: https://github.com/christophevg/mqfactory
Author: Christophe VG
License: MIT
Keywords: mq framework
Platform: UNKNOWN
Classifier: Environment :: Console
Classifier: Development Status :: 4 - Beta
Classifier: Intended Audience :: Developers
Classifier: Intended Audience :: System Administrators
Classifier: Topic :: Software Development
Classifier: License :: OSI Approved :: MIT License
Classifier: Programming Language :: Python
Classifier: Programming Language :: Python :: 2.7
Classifier: Programming Language :: Python :: 3.7
Requires-Dist: pymongo
Requires-Dist: paho-mqtt
Requires-Dist: cryptography
